{"current":{"color_background_body":"#ffffff","color_foreground_body":"#1a1a1a","color_foreground_body_dark":"#ffffff","color_background_primary":"#00f17c","color_foreground_primary":"#1a1a1a","color_background_secondary":"#1a1a1a","foreground_secondary_light":"#ffffff","color_background_tertiary":"#55cda1","color_foreground_tertiary":"#1a1a1a","color_bar":"#1e201c","color_background_overlay":"radial-gradient(rgba(0, 0, 0, 0.2), rgba(0, 0, 0, 0.4) 100%)","border_button_radius":45,"border_input_radius":30,"border_element_radius":2,"border_button_width":0,"border_input_width":1,"border_element_width":1,"input_button_style":"standard","input_field_border":"full","input_field_color_background":"color__bg-shade-2","input_field_color_border":"color__border-divider-1","type_font_body":"archivo_n4","type_font_heading":"archivo_n6","type_font_nav":"archivo_n4","type_base_size":15,"type_scale_ratio":114,"type_seperator":"dot","type_heading_capitilization":"uppercase","type_nav_capitilization":"","type_button_capitilization":"uppercase","type_icon_style":"sharp","header_links_desktop":"main-menu","header_links_mobile":"main-menu","header_position":"sticky","header_button_behavior":"click","header_overlap_desktop":80,"header_overlap_mobile":0,"header_blend":false,"x_margin":"window--narrow","gap_size":20,"enable_audio":false,"enable_animations":true,"enable_animated_images":true,"animate_header":"none","favicon":"shopify:\/\/shop_images\/favicon.png","product_card_color_scheme":"color__bg-body color__text","product_card_color_border":"","product_card_badge_scheme":"body","product_card_overlay_text":"!color__dark","product_card_color_overlay":"linear-gradient(0deg, rgba(0, 0, 0, 0.3), rgba(0, 0, 0, 0) 100%)","product_card_ratio":"aspect-[1\/1] aspect-w-1 aspect-h-1","product_card_crop":"cover","product_card_image_style":"standard","product_card_border_style":"thumbnail","product_card_alignment":"left","product_card_title_font":"type__body type--base","product_card_title_capitilization":"","product_card_stock_threshold":4,"product_card_savings_badge":"percent","product_card_enable_review_badge":false,"product_card_enable_review_text":true,"product_card_enable_vendor":false,"product_card_enable_swatches":true,"product_card_enable_sku":false,"product_card_enable_hover":true,"product_card_show_prices":true,"product_card_show_text_on_hover":false,"product_card_enable_tagline":true,"collection_card_color_scheme":"color__bg-body after:color__bg-body color__text","collection_card_color_border":"","collection_card_overlay_text":"!color__light","collection_card_color_overlay":"linear-gradient(0deg, rgba(0, 0, 0, 0.1), rgba(0, 0, 0, 0.1) 100%)","collection_card_ratio":"aspect-video","collection_card_crop":"cover","collection_card_border_style":"thumbnail","collection_card_title_font":"type__body type--base","collection_card_title_capitlization":"","blog_card_color_scheme":"color__bg-body after:color__bg-body color__text","blog_card_color_border":"","blog_card_badge_scheme":"body","blog_cards_color_overlay":"linear-gradient(0deg, rgba(0, 0, 0, 0), rgba(0, 0, 0, 0.3) 100%)","blog_card_ratio":"aspect-[2\/3] aspect-w-2 aspect-h-3","blog_card_border_style":"thumbnail","blog_card_title_font":"type__body type--base","blog_card_title_capitlization":"","blog_card_enable_author":false,"blog_card_enable_summary":true,"blog_card_enable_date":false,"blog_card_enable_tags":false,"enable_quick_mobile":false,"enable_quick_desktop":true,"enable_quick_image":true,"variant_selection":"dropdowns","plan_selection":"buttons","unavailable_indication":"selected","price_range":"show_starting_price","enable_zeros":false,"enable_currency":false,"pagination_type":"load","close_button_content":"icontext","close_button_color":"btn btn--minimal","enable_region":true,"enable_language":true,"enable_local_business":true,"social_tiktok_link":"","social_instagram_link":"https:\/\/www.instagram.com\/zoda_fit","social_twitter_link":"","social_facebook_link":"https:\/\/www.facebook.com\/zoda.sg\/","social_pinterest_link":"","social_snapchat_link":"","social_tumblr_link":"","social_discord_link":"","social_linkedin_link":"","social_twitch_link":"","social_youtube_link":"","social_vimeo_link":"","enable_search_author":true,"enable_search_body":true,"enable_search_barcode":true,"enable_search_sku":true,"enable_search_vendor":true,"layout_horizontal":"window--full","layout_header_position":"dynamic","layout_gap_size":1,"animated_header":"none","product_variant_selection":"dropdowns","search_author":true,"search_body":true,"search_tag":true,"search_variants_barcode":true,"search_variants_sku":true,"search_vendor":true,"price_enable_zeros":false,"price_enable_currency":false,"navigation_button_content":"icon","navigation_button_color":"btn btn--minimal","product_color_selection":"swatches","inputs_border_style":"bottom","inputs_color_background":"color__bg-shade-1","inputs_color_border":"color__border-selected-1","enable_animated_header":true,"thumbnails_color_scheme":"color__bg-body after:color__bg-body color__text","thumbnails_color_border":"outline--width color__outline-selected-1","product-cards_badge_scheme":"dark_outline","product-cards_overlay_background":"linear-gradient(180deg, rgba(255, 255, 255, 1), rgba(51, 61, 41, 1) 100%)","thumbnails_ratio":"aspect-[1\/1] aspect-w-1 aspect-h-1","thumbnails_object-sizing":"cover","thumbnails_border_style":"thumbnail","thumbnails_alignment":"justified","stock_threshold":15,"savings_badge":"percent","enable_thumbnails_variant_count":false,"enable_thumbnails_product_type":false,"enable_thumbnails_vendor":false,"enable_color_swatches":true,"enable_second_media_hover":false,"enable_tagline":true,"collection_cards_color_scheme":"color__bg-body after:color__bg-body color__text","collection_cards_color_border":"","collection_cards_color_background_overlay":"linear-gradient(180deg, rgba(30, 30, 30, 0.2), rgba(30, 30, 30, 0.1) 100%)","collection_cards_border_style":"thumbnail","blog_cards_color_scheme":"color__bg-body after:color__bg-body color__text","blog_cards_color_border":"","blog_cards_ratio":"aspect-video","blog_cards_border_style":"thumbnail","product-cards_color_background_overlay":"linear-gradient(180deg, rgba(30, 30, 30, 0.2) 4%, rgba(30, 30, 30, 0.1) 100%)","cart_behavior":"drawer","type_header":"body","type_thumbnail":"body","type_thumbnail_capitilization":"","color_background_body_dark":"#333333","border_dark":"#58544c","background_primary_dark":"#267683","foreground_primary_dark":"#fdfdfd","background_secondary_dark":"#fdfdfd","foreground_secondary_dark":"#333333","mobile_bar_dark":"#267683","logo":"shopify:\/\/shop_images\/COKx4K7qlPQCEAE.png","sections":{"theme__announcement":{"type":"theme__announcement","blocks":{"f2232503-8685-46db-aaf1-b796c5ea14f9":{"type":"announcement","settings":{"content":"<p>Make announcements or share a promotion.<\/p>"}},"493bfb93-68fd-473f-bc87-57abeae993ce":{"type":"announcement","settings":{"content":"<p>Make announcements or share a promotion.<\/p>"}}},"block_order":["f2232503-8685-46db-aaf1-b796c5ea14f9","493bfb93-68fd-473f-bc87-57abeae993ce"],"settings":{"color_scheme":"color__bg-primary color__primary","layout_alignment":"left","show_account_link":true}},"theme__header":{"type":"theme__header","blocks":{"e561cffb-e23b-4a10-8382-4959a1b99bf2":{"type":"content","settings":{"menu":"shop","heading":"Block heading","content":"<p>Describe a product, make announcements, or welcome customers to your store.&lt;<\/p>"}}},"block_order":["e561cffb-e23b-4a10-8382-4959a1b99bf2"],"settings":{"logo_desktop_height":45,"logo_mobile_height":16,"bar_layout_desktop":"left-below","bar_button_cart_type":"icon","bar_button_search_type":"icon","bar_button_login_type":"none","bar_button_menu_type":"icon","dropdown_color_scheme":"color__bg-body color__text","dropdown_color_border":"color__border-divider-1"}},"theme__menu":{"type":"theme__menu","blocks":{"announcement_EnhthP":{"type":"announcement","disabled":true,"settings":{"content":"<p>Make Announcement here<\/p>","color_scheme":"color__bg-primary color__primary","layout_x_alignment":"left"}},"image_ydWaBw":{"type":"image","settings":{"menu":"Homepage"}},"image_EG6caX":{"type":"image","disabled":true,"settings":{"menu":"Founding team","image":"shopify:\/\/shop_images\/col-2.png"}},"image_8EARaq":{"type":"image","disabled":true,"settings":{"menu":"About Zoda","image":"shopify:\/\/shop_images\/col-1.png"}},"collection_TK7hHC":{"type":"collection","disabled":true,"settings":{"menu":"Product listing","collection":"lorem-ipsum-title-5"}},"image_HD8MLt":{"type":"image","disabled":true,"settings":{"menu":"Product page","image":"shopify:\/\/shop_images\/col-4.png"}},"image_8z6fKt":{"type":"image","disabled":true,"settings":{"menu":"Contact us","image":"shopify:\/\/shop_images\/COMMUNITY.png"}}},"block_order":["announcement_EnhthP","image_ydWaBw","image_EG6caX","image_8EARaq","collection_TK7hHC","image_HD8MLt","image_8z6fKt"],"settings":{"top_color_scheme":"color__bg-tertiary color__tertiary","top_color_border":"color__border-divider-1","main_color_scheme":"color__bg-body color__text","main_color_border":"color__border-divider-1","show_search":false,"bottom_color_scheme":"color__bg-tertiary color__tertiary","bottom_color_border":"color__border-divider-1"}},"theme__cart":{"type":"theme__cart","blocks":{"content_9NVwUf":{"type":"content","disabled":true,"settings":{"heading":"Buy 2 Save 25%","content":"<p>Buy two necklaces and save 25%. Discount added to cart automatically<\/p>","button_label":"","url":"","enable_autoplay":true,"enable_mute_toggle":true,"enable_loop":true,"spacing_minimum_height":250,"enable_padding":true,"color_scheme":"color__bg-tertiary color__tertiary","color_border":"outline--width color__outline-divider-1","color_text":"color__text","color_button":"btn--small btn--plain !color__text","enable_gradient":false,"layout_y_alignment":"justify-end","layout_x_alignment":"left"}},"upsell_featured_BpWVBM":{"type":"upsell_featured","disabled":true,"settings":{"products":"lorem-ipsum-title-5"}},"progress_bar_YriDW4":{"type":"progress_bar","settings":{"threshold":150,"calculation":"total","success":"Congrats! You've unlocked free shipping."}},"empty_cart_Kt6Fyp":{"type":"empty_cart","disabled":true,"settings":{"heading":"Block heading","content":"<p>Describe a product, make announcements, or inform customers about a promotion.<\/p>","button_label":"Button","url":"shopify:\/\/collections\/all","enable_autoplay":true,"enable_mute_toggle":true,"enable_loop":true,"spacing_minimum_height":250,"enable_padding":true,"color_scheme":"color__bg-body color__text","color_border":"outline--width color__outline-divider-1","color_text":"color__text","color_button":"btn--small btn--plain !color__text","enable_gradient":false,"layout_y_alignment":"justify-end","layout_x_alignment":"left"}},"announcement_7a3bgj":{"type":"announcement","settings":{"content":"<p>Spend a minimum of SGD$150 to unlock free shipping!<\/p>","color_scheme":"color__bg-secondary color__secondary","layout_x_alignment":"left"}}},"block_order":["content_9NVwUf","upsell_featured_BpWVBM","progress_bar_YriDW4","empty_cart_Kt6Fyp","announcement_7a3bgj"],"settings":{"top_color_scheme":"color__bg-tertiary color__tertiary","top_color_border":"color__border-divider-1","main_color_scheme_first":"color__bg-body color__text","main_color_scheme_second":"color__bg-body color__text","main_color_border":"!color__border-transparent","main_enable_cart_note":true,"main_enable_cart_share":true,"main_enable_cart_sku":true,"bottom_color_scheme":"color__bg-body color__text","bottom_color_border":"!color__border-transparent","bottom_color_button":"btn btn--secondary","cart_button_behavior":"checkout","bottom_disclaimer":"","show_continue_shopping_button":true,"show_button_prices":true,"show_cart_subtotals":true}},"theme__footer":{"type":"theme__footer","blocks":{"78204a1a-1009-4f50-a9c8-4a9f0b2af321":{"type":"newsletter","settings":{"heading":"Newsletter","content":"<p>Tell customers why they should subscribe to your newsletter.<\/p>","button":"Subscribe","disclaimer":"<p>Include an additonal disclaimer to clarify how you will use a subscribers email.<\/p>","success":"<p>Success! You’ve been subscribed.<\/p>"}},"5dc22179-9717-40d2-9d83-4532c904e6d1":{"type":"menu","settings":{"menu":"footer"}},"150805eb-9862-49dd-b0c2-0111162d6fce":{"type":"menu","settings":{"menu":"footer"}},"6ad6b950-210d-4cf8-b231-62c67db4980e":{"type":"menu","settings":{"menu":"footer"}}},"block_order":["78204a1a-1009-4f50-a9c8-4a9f0b2af321","5dc22179-9717-40d2-9d83-4532c904e6d1","150805eb-9862-49dd-b0c2-0111162d6fce","6ad6b950-210d-4cf8-b231-62c67db4980e"],"settings":{"main_color_scheme":"color__bg-overlay-1 color__text","main_color_border":"color__border-divider-1","main_color_button":"btn btn--secondary","sub_color_scheme":"color__bg-overlay-1 color__text","sub_color_border":"color__border-divider-1","sub_links":"footer"}},"theme__age-verification":{"type":"theme__age-verification","settings":{"age_verification_style":"full_date","age_limit":18,"heading":"Verify your age","content":"<p>Please confirm that you are over the age of 18 to proceed.<\/p>"}},"theme__search":{"type":"theme__search","settings":{"search_links":"main-menu","top_color_scheme":"color__bg-body color__text","top_color_border":"color__border-divider-1","main_color_scheme":"color__bg-body color__text","main_color_border":"color__border-divider-1"}},"theme__min-header":{"type":"theme__min-header","settings":{"logo_default":"shopify:\/\/shop_images\/logo.svg","logo_overlay":"shopify:\/\/shop_images\/logo-white.svg","logo_desktop_height":37,"logo_mobile_height":37,"bar_layout_desktop":"left","bar_default_color_scheme":"color__bg-body color__text","bar_overlay_color_scheme":"color__bg-body color__text","bar_default_color_border":"color__border-divider-1","bar_overlay_color_border":"color__border-divider-1","bar_capitilization":"","bar_font":"type__body","visibility":""}}},"content_for_index":[],"blocks":{"1232542678405107163":{"type":"shopify:\/\/apps\/instafeed\/blocks\/head-block\/c447db20-095d-4a10-9725-b5977662c9d5","disabled":false,"settings":{}},"855628211100114053":{"type":"shopify:\/\/apps\/klaviyo-email-marketing-sms\/blocks\/klaviyo-onsite-embed\/2632fe16-c075-4321-a88b-50b567f42507","disabled":false,"settings":{}},"4651250007506174373":{"type":"shopify:\/\/apps\/mageplaza-instagram-feed\/blocks\/app_embed\/2e85b90f-5da9-4654-967e-051f1942340c","disabled":false,"settings":{}},"pagefly-page-builder":{"type":"shopify:\/\/apps\/pagefly-page-builder\/blocks\/app-embed\/83e179f7-59a0-4589-8c66-c0dddf959200","disabled":false,"settings":{}},"6174324309569838175":{"type":"shopify:\/\/apps\/smile-io\/blocks\/smile-shopify-app\/2fae4e25-1841-4ea2-bc02-bd548478c4f6","disabled":true,"settings":{}}}},"presets":{"Shimmer":{"color_background_body":"#ffffff","color_foreground_body":"#1e201c","color_foreground_body_dark":"#f2eee2","color_background_primary":"#1e201c","color_foreground_primary":"#f2eee2","color_background_secondary":"#1e201c","foreground_secondary_light":"#f2eee2","color_background_tertiary":"#f2eee2","color_foreground_tertiary":"#1e201c","color_bar":"#1e201c","color_background_overlay":"radial-gradient(rgba(0, 0, 0, 0.2), rgba(0, 0, 0, 0.4) 100%)","border_button_radius":0,"border_input_radius":0,"border_element_radius":0,"border_input_width":1,"input_field_border":"none","type_font_body":"inter_n4","type_font_heading":"din_next_n9","type_font_nav":"inter_n4","type_base_size":14,"type_scale_ratio":116,"type_seperator":"dot","type_heading_capitilization":"uppercase","type_nav_capitilization":"","type_button_capitilization":"","header_links_mobile":"main-menu","header_position":"sticky","header_button_behavior":"click","x_margin":"window--wide","gap_size":1,"enable_audio":false,"enable_animations":true,"enable_animated_images":true,"animate_header":"none","favicon":"shopify:\/\/shop_images\/Impact.png","product_card_color_border":"outline--width color__outline-selected-1","product_card_badge_scheme":"body","product_card_color_overlay":"linear-gradient(0deg, rgba(0, 0, 0, 0.3), rgba(0, 0, 0, 0) 100%)","product_card_ratio":"aspect-[1\/1] aspect-w-1 aspect-h-1","product_card_border_style":"thumbnail","product_card_alignment":"left","product_card_stock_threshold":4,"product_card_savings_badge":"percent","product_card_enable_review_badge":false,"product_card_enable_review_text":true,"product_card_enable_swatches":false,"product_card_show_prices":true,"product_card_show_text_on_hover":true,"collection_card_color_scheme":"color__bg-shade-1 after:color__bg-shade-1 color__text","collection_card_color_border":"outline--width color__outline-selected-1","collection_card_color_overlay":"linear-gradient(0deg, rgba(0, 0, 0, 0), rgba(0, 0, 0, 0.3) 100%)","collection_card_ratio":"aspect-[1\/1] aspect-w-1 aspect-h-1","collection_card_border_style":"thumbnail","blog_card_color_scheme":"color__bg-shade-1 after:color__bg-shade-1 color__text","blog_card_color_border":"outline--width color__outline-selected-1","blog_card_badge_scheme":"body","blog_cards_color_overlay":"linear-gradient(0deg, rgba(0, 0, 0, 0), rgba(0, 0, 0, 0.3) 100%)","blog_card_ratio":"aspect-video","blog_card_border_style":"thumbnail","blog_card_enable_author":true,"blog_card_enable_tags":true,"enable_quick_mobile":false,"enable_quick_desktop":true,"enable_quick_image":true,"unavailable_indication":"selected","enable_zeros":false,"enable_currency":false,"pagination_type":"load","close_button_content":"text","enable_region":true,"enable_language":true,"enable_local_business":true,"social_tiktok_link":"","social_instagram_link":"","social_twitter_link":"","social_facebook_link":"","social_pinterest_link":"","social_snapchat_link":"","social_tumblr_link":"","social_discord_link":"","social_linkedin_link":"","social_twitch_link":"","social_youtube_link":"","social_vimeo_link":"","layout_horizontal":"window--full","layout_gap_size":1,"animated_header":"none","product_variant_selection":"dropdowns","search_author":true,"search_body":true,"search_tag":true,"search_variants_barcode":true,"search_variants_sku":true,"search_vendor":true,"price_enable_zeros":false,"price_enable_currency":false,"navigation_button_content":"icon","navigation_button_color":"btn btn--minimal","product_color_selection":"swatches","inputs_border_style":"bottom","inputs_color_background":"color__bg-shade-1","inputs_color_border":"color__border-selected-1","enable_animated_header":true,"thumbnails_color_scheme":"color__bg-body after:color__bg-body color__text","thumbnails_color_border":"outline--width color__outline-selected-1","product-cards_badge_scheme":"dark_outline","product-cards_overlay_background":"linear-gradient(180deg, rgba(255, 255, 255, 1), rgba(51, 61, 41, 1) 100%)","thumbnails_ratio":"aspect-[1\/1] aspect-w-1 aspect-h-1","thumbnails_object-sizing":"cover","thumbnails_border_style":"thumbnail","thumbnails_alignment":"justified","stock_threshold":15,"savings_badge":"percent","enable_thumbnails_variant_count":false,"enable_thumbnails_product_type":false,"enable_thumbnails_vendor":false,"enable_color_swatches":true,"enable_second_media_hover":false,"enable_tagline":true,"collection_cards_color_scheme":"color__bg-body after:color__bg-body color__text","collection_cards_color_border":"","collection_cards_color_background_overlay":"linear-gradient(180deg, rgba(30, 30, 30, 0.2), rgba(30, 30, 30, 0.1) 100%)","collection_cards_border_style":"thumbnail","blog_cards_color_scheme":"color__bg-body after:color__bg-body color__text","blog_cards_color_border":"","blog_cards_ratio":"aspect-video","blog_cards_border_style":"thumbnail","product-cards_color_background_overlay":"linear-gradient(180deg, rgba(30, 30, 30, 0.2) 4%, rgba(30, 30, 30, 0.1) 100%)","cart_behavior":"drawer","type_header":"body","type_thumbnail":"body","type_thumbnail_capitilization":"","color_background_body_dark":"#333333","border_dark":"#58544c","background_primary_dark":"#267683","foreground_primary_dark":"#fdfdfd","background_secondary_dark":"#fdfdfd","foreground_secondary_dark":"#333333","mobile_bar_dark":"#267683","logo":"shopify:\/\/shop_images\/COKx4K7qlPQCEAE.png","sections":{"theme__announcement":{"type":"theme__announcement","blocks":{"f2232503-8685-46db-aaf1-b796c5ea14f9":{"type":"announcement","settings":{"content":"<p>Make announcements or share a promotion.<\/p>"}},"493bfb93-68fd-473f-bc87-57abeae993ce":{"type":"announcement","settings":{"content":"<p>Make announcements or share a promotion.<\/p>"}}},"block_order":["f2232503-8685-46db-aaf1-b796c5ea14f9","493bfb93-68fd-473f-bc87-57abeae993ce"],"settings":{"color_scheme":"color__bg-primary color__primary","layout_alignment":"left","show_account_link":true}},"theme__header":{"type":"theme__header","blocks":{"e561cffb-e23b-4a10-8382-4959a1b99bf2":{"type":"content","settings":{"menu":"shop","heading":"Block heading","content":"<p>Describe a product, make announcements, or welcome customers to your store.&lt;<\/p>"}}},"block_order":["e561cffb-e23b-4a10-8382-4959a1b99bf2"],"settings":{"logo_desktop_height":45,"logo_mobile_height":16,"bar_layout_desktop":"left-below","bar_button_cart_type":"icon","bar_button_search_type":"icon","bar_button_login_type":"none","bar_button_menu_type":"icon","dropdown_color_scheme":"color__bg-body color__text","dropdown_color_border":"color__border-divider-1"}},"theme__menu":{"type":"theme__menu","blocks":{"image_ydWaBw":{"type":"image","settings":{"menu":"Earrings","image":"shopify:\/\/shop_images\/pexels-created-stories-11456370fawiohfwa.png"}},"image_EG6caX":{"type":"image","settings":{"menu":"Necklaces","image":"shopify:\/\/shop_images\/nothirdnecklace.png"}},"image_8EARaq":{"type":"image","settings":{"menu":"Rings","image":"shopify:\/\/shop_images\/pexels-pnw-production-9218400_1_fawaw.png"}}},"block_order":["image_ydWaBw","image_EG6caX","image_8EARaq"],"settings":{"top_color_scheme":"color__bg-tertiary color__tertiary","top_color_border":"color__border-divider-1","main_color_scheme":"color__bg-tertiary color__tertiary","main_color_border":"color__border-divider-1","show_search":true,"bottom_color_scheme":"color__bg-tertiary color__tertiary","bottom_color_border":"color__border-divider-1"}},"theme__cart":{"type":"theme__cart","blocks":{"content_9NVwUf":{"type":"content","settings":{"heading":"Buy 2 Save 25%","content":"<p>Buy two necklaces and save 25%. Discount added to cart automatically<\/p>","button_label":"","url":"","enable_autoplay":true,"enable_mute_toggle":true,"enable_loop":true,"spacing_minimum_height":250,"enable_padding":true,"color_scheme":"color__bg-tertiary color__tertiary","color_border":"outline--width color__outline-divider-1","color_text":"color__text","color_button":"btn--small btn--plain !color__text","enable_gradient":false,"layout_y_alignment":"justify-end","layout_x_alignment":"left"}},"upsell_featured_BpWVBM":{"type":"upsell_featured","settings":{"products":"upsell"}}},"block_order":["content_9NVwUf","upsell_featured_BpWVBM"],"settings":{"top_color_scheme":"color__bg-tertiary color__tertiary","top_color_border":"color__border-divider-1","main_color_scheme_first":"color__bg-tertiary color__tertiary","main_color_scheme_second":"color__bg-tertiary color__tertiary","main_color_border":"color__border-divider-1","main_enable_cart_note":true,"main_enable_cart_share":true,"main_enable_cart_sku":false,"bottom_color_scheme":"color__bg-tertiary color__tertiary","bottom_color_border":"color__border-divider-1","bottom_color_button":"btn","cart_button_behavior":"checkout","bottom_disclaimer":"","show_continue_shopping_button":false,"show_button_prices":true,"show_cart_subtotals":true}},"theme__footer":{"type":"theme__footer","blocks":{"78204a1a-1009-4f50-a9c8-4a9f0b2af321":{"type":"newsletter","settings":{"heading":"Newsletter","content":"<p>Tell customers why they should subscribe to your newsletter.<\/p>","button":"Subscribe","disclaimer":"<p>Include an additonal disclaimer to clarify how you will use a subscribers email.<\/p>","success":"<p>Success! You’ve been subscribed.<\/p>"}},"5dc22179-9717-40d2-9d83-4532c904e6d1":{"type":"menu","settings":{"menu":"footer"}},"150805eb-9862-49dd-b0c2-0111162d6fce":{"type":"menu","settings":{"menu":"footer"}},"6ad6b950-210d-4cf8-b231-62c67db4980e":{"type":"menu","settings":{"menu":"footer"}}},"block_order":["78204a1a-1009-4f50-a9c8-4a9f0b2af321","5dc22179-9717-40d2-9d83-4532c904e6d1","150805eb-9862-49dd-b0c2-0111162d6fce","6ad6b950-210d-4cf8-b231-62c67db4980e"],"settings":{"main_color_scheme":"color__bg-overlay-1 color__text","main_color_border":"color__border-divider-1","main_color_button":"btn btn--secondary","sub_color_scheme":"color__bg-overlay-1 color__text","sub_color_border":"color__border-divider-1","sub_links":"footer"}},"theme__age-verification":{"type":"theme__age-verification","settings":{"age_verification_style":"full_date","age_limit":18,"heading":"Verify your age","content":"<p>Please confirm that you are over the age of 18 to proceed.<\/p>"}},"theme__search":{"type":"theme__search","settings":{"search_links":"main-menu","top_color_scheme":"color__bg-tertiary color__tertiary","top_color_border":"color__border-divider-1","main_color_scheme":"color__bg-tertiary color__tertiary","main_color_border":"color__border-divider-1"}}},"content_for_index":[]},"Swift":{"color_background_body":"#ffffff","color_foreground_body":"#1a1a1a","color_foreground_body_dark":"#ffffff","color_background_primary":"#e7ea1f","color_foreground_primary":"#1a1a1a","color_background_secondary":"#1a1a1a","foreground_secondary_light":"#ffffff","color_background_tertiary":"#559cad","color_foreground_tertiary":"#1a1a1a","color_bar":"#1a1a1a","color_background_overlay":"radial-gradient(rgba(0, 0, 0, 0.2), rgba(0, 0, 0, 0.4) 100%)","border_button_radius":50,"border_input_radius":50,"border_element_radius":4,"border_button_width":1,"border_input_width":1,"border_element_width":1,"input_field_border":"none","type_font_body":"arimo_n4","type_font_heading":"arimo_n4","type_font_nav":"arimo_n4","type_base_size":16,"type_scale_ratio":122,"type_seperator":"dot","type_heading_capitilization":"","type_button_capitilization":"","header_links_mobile":"main-menu","header_position":"dynamic","header_button_behavior":"click","x_margin":"window--wide","gap_size":20,"enable_audio":true,"enable_animations":true,"enable_animated_images":true,"animate_header":"fade","favicon":"shopify:\/\/shop_images\/Impact.png","product_card_color_scheme":"color__bg-body color__text","product_card_color_border":"","product_card_badge_scheme":"secondary","product_card_color_overlay":"linear-gradient(0deg, rgba(0, 0, 0, 0.1), rgba(0, 0, 0, 0.1) 100%)","product_card_ratio":"aspect-[1\/1] aspect-w-1 aspect-h-1","product_card_border_style":"thumbnail","product_card_stock_threshold":100,"product_card_savings_badge":"percent","product_card_enable_review_badge":false,"product_card_enable_review_text":false,"collection_card_color_scheme":"color__bg-body after:color__bg-body color__text","collection_card_color_border":"","collection_card_color_overlay":"linear-gradient(0deg, rgba(0, 0, 0, 0.1), rgba(0, 0, 0, 0.1) 100%)","collection_card_ratio":"aspect-video","collection_card_border_style":"thumbnail","collection_card_enable_size":true,"collection_card_enable_description":false,"blog_card_color_scheme":"color__bg-body after:color__bg-body color__text","blog_card_color_border":"","blog_card_badge_scheme":"secondary","blog_cards_color_overlay":"linear-gradient(0deg, rgba(0, 0, 0, 0.2), rgba(0, 0, 0, 0.2) 100%)","blog_card_ratio":"aspect-[2\/3] aspect-w-2 aspect-h-3","blog_card_border_style":"thumbnail","blog_card_enable_author":false,"blog_card_enable_date":false,"blog_card_enable_tags":true,"enable_quick_mobile":false,"enable_quick_desktop":true,"enable_quick_image":true,"unavailable_indication":"selected","cart_behavior_desktop":"drawer","enable_zeros":false,"enable_currency":false,"pagination_type":"scroll","enable_region":true,"enable_language":true,"enable_local_business":true,"social_tiktok_link":"","social_instagram_link":"","social_twitter_link":"","social_facebook_link":"","social_pinterest_link":"","social_snapchat_link":"","social_tumblr_link":"","social_discord_link":"","social_linkedin_link":"","social_twitch_link":"","social_youtube_link":"","social_vimeo_link":"","layout_horizontal":"window--wide","layout_gap_size":10,"product_variant_selection":"buttons","search_author":true,"search_body":true,"search_tag":true,"search_variants_barcode":true,"search_variants_sku":true,"search_vendor":true,"price_enable_currency":false,"navigation_button_content":"icon","product_color_selection":"swatches","inputs_border_style":"none","inputs_color_background":"color__bg-shade-1","inputs_color_border":"color__border-selected-1","enable_animated_header":true,"thumbnails_color_scheme":"color__bg-shade-1 after:color__bg-shade-1 color__text","thumbnails_color_border":"","product-cards_overlay_background":"linear-gradient(180deg, rgba(255, 255, 255, 1), rgba(85, 156, 173, 1) 100%)","thumbnails_ratio":"aspect-[1\/1] aspect-w-1 aspect-h-1","thumbnails_object-sizing":"cover","thumbnails_border_style":"thumbnail","thumbnails_alignment":"justified","stock_threshold":2,"savings_badge":"percent","enable_thumbnails_variant_count":true,"enable_thumbnails_product_type":false,"enable_thumbnails_vendor":false,"enable_color_swatches":true,"enable_second_media_hover":true,"enable_tagline":true,"collection_cards_color_scheme":"color__bg-shade-1 after:color__bg-shade-1 color__text","collection_cards_color_border":"","collection_cards_color_background_overlay":"linear-gradient(180deg, rgba(85, 156, 173, 1), rgba(30, 30, 30, 0.1) 100%)","collection_cards_ratio":"aspect-[2\/3] aspect-w-2 aspect-h-3","collection_cards_border_style":"thumbnail","collection_cards_title_font":"type__heading type--big","collection_cards_enable_size":false,"blog_cards_color_scheme":"color__bg-neutral after:color__bg-neutral color__text","blog_cards_color_border":"","blog_cards_color_background_overlay":"linear-gradient(180deg, rgba(255, 255, 255, 1), rgba(0, 0, 0, 1) 100%)","blog_cards_ratio":"aspect-[2\/3] aspect-w-2 aspect-h-3","blog_cards_border_style":"thumbnail","blog_cards_enable_author":false,"blog_cards_enable_date":false,"product-cards_color_background_overlay":"linear-gradient(180deg, rgba(30, 30, 30, 0.2) 4%, rgba(30, 30, 30, 0.1) 100%)","cart_behavior":"drawer","type_header":"body","type_thumbnail":"body","type_thumbnail_capitilization":"","color_background_body_dark":"#333333","border_dark":"#58544c","background_primary_dark":"#267683","foreground_primary_dark":"#fdfdfd","background_secondary_dark":"#fdfdfd","foreground_secondary_dark":"#333333","mobile_bar_dark":"#267683","logo":"shopify:\/\/shop_images\/COKx4K7qlPQCEAE.png","sections":{"theme__menu":{"type":"theme__menu","blocks":{"announcement_NPRyhD":{"type":"announcement","settings":{"content":"<p>Make announcements or share a promotion.<\/p>","color_scheme":"color__bg-secondary color__secondary","layout_x_alignment":"left"}},"8ada66de-e98a-4f05-82e8-90e4dba2257b":{"type":"image","settings":{"menu":"Women","image":"shopify:\/\/shop_images\/pexels-maksim-goncharenok-4348633.png"}},"collection_xtE8bJ":{"type":"collection","settings":{"menu":"men","collection":"men"}},"2a8f3ca6-06cc-4dd8-8d4f-4edde48f45c8":{"type":"image","settings":{"menu":"Trail","image":"shopify:\/\/shop_images\/trail_snow.png"}},"6c1678f1-cb78-4637-84e8-e57f11f1ec35":{"type":"image","settings":{"menu":"Road","image":"shopify:\/\/shop_images\/pexels-tembela-bohle-2803158.jpg"}}},"block_order":["announcement_NPRyhD","8ada66de-e98a-4f05-82e8-90e4dba2257b","collection_xtE8bJ","2a8f3ca6-06cc-4dd8-8d4f-4edde48f45c8","6c1678f1-cb78-4637-84e8-e57f11f1ec35"],"settings":{"top_color_scheme":"color__bg-overlay-1 color__text","top_color_border":"color__border-divider-1","main_color_scheme":"color__bg-overlay-1 color__text","main_color_border":"!color__border-transparent","show_search":true,"bottom_color_scheme":"color__bg-overlay-1 color__text","bottom_color_border":"color__border-divider-1"}},"theme__cart":{"type":"theme__cart","blocks":{"announcement_diJAW3":{"type":"announcement","settings":{"content":"<p>BOGO 50% off all Archers<\/p>","color_scheme":"color__bg-secondary color__secondary","layout_x_alignment":"left"}},"upsell_featured_4VnHqA":{"type":"upsell_featured","settings":{"products":"best-sellers"}},"upsell_checkbox_AAhNFQ":{"type":"upsell_checkbox","settings":{"variant_id":"","label":"Add shipping protection - $5"}},"progress_bar_EUYJET":{"type":"progress_bar","settings":{"threshold":100,"calculation":"total","success":"Congrats! You've unlocked free shipping."}},"empty_cart_cRJjji":{"type":"empty_cart","settings":{"heading":"Block heading","content":"<p>Describe a product, make announcements, or inform customers about a promotion.<\/p>","button_label":"Button","url":"shopify:\/\/collections\/all","enable_autoplay":true,"enable_mute_toggle":true,"enable_loop":true,"spacing_minimum_height":250,"enable_padding":true,"color_scheme":"color__bg-body color__text","color_border":"outline--width color__outline-divider-1","color_text":"color__text","color_button":"btn--small btn--plain !color__text","enable_gradient":false,"layout_y_alignment":"justify-end","layout_x_alignment":"left"}}},"block_order":["announcement_diJAW3","upsell_featured_4VnHqA","upsell_checkbox_AAhNFQ","progress_bar_EUYJET","empty_cart_cRJjji"],"settings":{"top_color_scheme":"color__bg-overlay-1 color__text","top_color_border":"color__border-divider-1","main_color_scheme_first":"color__bg-overlay-1 color__text","main_color_scheme_second":"color__bg-overlay-1 color__text","main_color_border":"color__border-divider-1","main_enable_cart_note":false,"main_enable_cart_share":true,"main_enable_cart_sku":false,"bottom_color_scheme":"color__bg-overlay-1 color__text","bottom_color_border":"!color__border-transparent","bottom_color_button":"btn","cart_button_behavior":"checkout","bottom_disclaimer":"","show_continue_shopping_button":false,"show_button_prices":true,"show_cart_subtotals":true}},"theme__footer":{"type":"theme__footer","blocks":{"78204a1a-1009-4f50-a9c8-4a9f0b2af321":{"type":"newsletter","settings":{"heading":"Newsletter","content":"<p>Tell customers why they should subscribe to your newsletter.<\/p>","button":"Subscribe","disclaimer":"<p>Include an additonal disclaimer to clarify how you will use a subscribers email.<\/p>","success":"<p>Success! You’ve been subscribed.<\/p>"}},"5dc22179-9717-40d2-9d83-4532c904e6d1":{"type":"menu","settings":{"menu":"footer"}},"150805eb-9862-49dd-b0c2-0111162d6fce":{"type":"menu","settings":{"menu":"footer"}},"6ad6b950-210d-4cf8-b231-62c67db4980e":{"type":"menu","settings":{"menu":"footer"}}},"block_order":["78204a1a-1009-4f50-a9c8-4a9f0b2af321","5dc22179-9717-40d2-9d83-4532c904e6d1","150805eb-9862-49dd-b0c2-0111162d6fce","6ad6b950-210d-4cf8-b231-62c67db4980e"],"settings":{"main_color_scheme":"color__bg-overlay-1 color__text","main_color_border":"color__border-divider-1","main_color_button":"btn btn--secondary","sub_color_scheme":"color__bg-overlay-1 color__text","sub_color_border":"color__border-divider-1","sub_links":"footer"}},"theme__age-verification":{"type":"theme__age-verification","settings":{"age_verification_style":"full_date","age_limit":18,"heading":"Verify your age","content":"<p>Please confirm that you are over the age of 18 to proceed.<\/p>"}},"theme__search":{"type":"theme__search","blocks":{"announcement_zwGkmE":{"type":"announcement","settings":{"content":"<p>Make announcements or share a promotion.<\/p>","color_scheme":"color__bg-secondary color__secondary","layout_x_alignment":"left"}}},"block_order":["announcement_zwGkmE"],"settings":{"search_links":"main-menu","top_color_scheme":"color__bg-body color__text","top_color_border":"color__border-divider-1","main_color_scheme":"color__bg-body color__text","main_color_border":"!color__border-transparent"}}},"content_for_index":[]},"Silk":{"color_background_body":"#eae0d5","color_foreground_body":"#22333b","color_foreground_body_dark":"#eae0d5","color_background_primary":"#5e503f","color_foreground_primary":"#eae0d5","color_background_secondary":"#c6ac8f","foreground_secondary_light":"#22333b","color_background_tertiary":"#eae0d5","color_foreground_tertiary":"#5e503f","color_bar":"#eae0d5","border_button_radius":0,"border_input_radius":0,"border_element_radius":0,"border_button_width":2,"input_field_border":"none","type_font_body":"sans-serif","type_font_heading":"itc_clearface_n7","type_font_nav":"sans-serif","type_base_size":14,"type_scale_ratio":122,"type_seperator":"line","type_heading_capitilization":"","header_links_desktop":"shop","header_links_mobile":"mobile-main","header_links_submenu":"","header_position":"dynamic","header_overlap_desktop":90,"header_overlap_mobile":60,"header_blend":false,"x_margin":"window--wide","gap_size":5,"enable_audio":false,"enable_animations":true,"enable_animated_images":true,"product_card_color_scheme":"color__bg-overlay-1 color__text","product_card_color_border":"","product_card_badge_scheme":"neutral","product_card_color_overlay":"linear-gradient(0deg, rgba(0, 0, 0, 0), rgba(0, 0, 0, 0) 100%)","product_card_ratio":"aspect-[1\/1] aspect-w-1 aspect-h-1","product_card_image_style":"slider","product_card_border_style":"thumbnail","product_card_alignment":"justified","product_card_stock_threshold":100,"product_card_savings_badge":"percent","product_card_enable_review_badge":true,"product_card_enable_review_text":false,"product_card_show_prices":true,"collection_card_color_scheme":"color__bg-overlay-1 after:color__bg-overlay-1 color__text","collection_card_color_border":"","collection_card_color_overlay":"linear-gradient(0deg, rgba(0, 0, 0, 0.2), rgba(0, 0, 0, 0.3) 100%)","collection_card_border_style":"thumbnail","blog_card_color_scheme":"color__bg-overlay-1 after:color__bg-overlay-1 color__text","blog_card_color_border":"","blog_card_badge_scheme":"neutral","blog_cards_color_overlay":"linear-gradient(0deg, rgba(0, 0, 0, 0.2), rgba(0, 0, 0, 0.4) 100%)","blog_card_ratio":"aspect-[1\/1] aspect-w-1 aspect-h-1","blog_card_border_style":"thumbnail","blog_card_enable_author":true,"blog_card_enable_date":true,"blog_card_enable_tags":true,"enable_quick_mobile":false,"enable_quick_desktop":true,"enable_quick_image":true,"unavailable_indication":"selected","cart_behavior_desktop":"alert","price_range":"show_starting_price","enable_zeros":false,"enable_currency":false,"pagination_type":"scroll","close_button_content":"icon","enable_region":true,"enable_language":true,"social_tiktok_link":"https:\/\/tiktok.com\/@shopify","social_instagram_link":"http:\/\/instagram.com\/shopify","header_overlap":82,"layout_horizontal":"window--full","layout_header_position":"relative","layout_gap_size":1,"animated_header":"fade","product_variant_selection":"dropdowns","product_plan_selection":"buttons","search_author":true,"search_body":true,"search_variants_barcode":true,"search_variants_sku":true,"search_vendor":true,"price_enable_zeros":false,"price_enable_currency":false,"navigation_button_content":"icon","navigation_button_color":"btn btn--minimal","quick_color_button":"btn btn--plain","sections":{"theme__cart":{"type":"theme__cart","blocks":{"progress_bar_JVinQ9":{"type":"progress_bar","settings":{"threshold":100,"calculation":"total","success":"Congrats! You've unlocked free shipping."}},"upsell_checkbox_bx87CL":{"type":"upsell_checkbox","settings":{"variant_id":"48577398702372","label":"Add shipping protection - $15"}}},"block_order":["progress_bar_JVinQ9","upsell_checkbox_bx87CL"],"settings":{"top_color_scheme":"color__bg-body color__text","top_color_border":"color__border-divider-1","main_color_scheme_first":"color__bg-body color__text","main_color_scheme_second":"color__bg-body color__text","main_color_border":"color__border-divider-1","main_enable_cart_note":true,"main_enable_cart_share":true,"main_enable_cart_sku":false,"bottom_color_scheme":"color__bg-body color__text","bottom_color_border":"color__border-divider-1","bottom_color_button":"btn","cart_button_behavior":"checkout","bottom_disclaimer":"","show_continue_shopping_button":false,"show_button_prices":true,"show_cart_subtotals":false}},"theme__menu":{"type":"theme__menu","blocks":{"content_AxPjhN":{"type":"content","settings":{"heading":"Studio Tours","content":"<p>456 Main Street<br\/>Simcoe County<\/p><p><\/p>","button_label":"Learn more","url":"shopify:\/\/pages\/studio-tours","enable_autoplay":true,"enable_mute_toggle":true,"enable_loop":true,"spacing_minimum_height":0,"enable_padding":true,"color_scheme":"color__bg-overlay-1 color__text","color_border":"","color_text":"color__text","color_button":"btn--small !color__primary","enable_gradient":false,"layout_y_alignment":"justify-end","layout_x_alignment":"left"}}},"block_order":["content_AxPjhN"],"settings":{"top_color_scheme":"color__bg-body color__text","top_color_border":"!color__border-transparent","main_color_scheme":"color__bg-body color__text","main_color_border":"color__border-divider-1","show_search":false,"bottom_color_scheme":"color__bg-body color__text","bottom_color_border":"color__border-divider-1"}},"theme__search":{"type":"theme__search","blocks":{"announcement_86ABQJ":{"type":"announcement","settings":{"content":"<p>Make announcements or share a promotion.<\/p>","color_scheme":"color__bg-secondary color__secondary","layout_x_alignment":"left"}}},"block_order":["announcement_86ABQJ"],"settings":{"search_links":"","top_color_scheme":"color__bg-body color__text","top_color_border":"color__border-divider-1","main_color_scheme":"color__bg-body color__text","main_color_border":"color__border-divider-1"}}},"content_for_index":[],"blocks":{"14060646107696862457":{"type":"shopify:\/\/apps\/judge-me-reviews\/blocks\/judgeme_core\/61ccd3b1-a9f2-4160-9fe9-4fec8413e5d8","disabled":true,"settings":{}}}},"Spice":{"color_background_body":"#fff4eb","color_foreground_body":"#7d3d00","color_foreground_body_dark":"#fff4eb","color_background_primary":"#7d0041","color_foreground_primary":"#fff4eb","color_background_secondary":"#bb060a","foreground_secondary_light":"#fff4eb","color_background_tertiary":"#7d3d00","color_foreground_tertiary":"#fff4eb","color_bar":"#fff4eb","border_input_radius":15,"border_element_radius":15,"border_button_width":2,"border_input_width":1,"border_element_width":1,"input_field_border":"full","input_field_color_border":"color__border-divider-1","type_font_body":"itc_stepp_n4","type_font_heading":"itc_stepp_n4","type_font_nav":"itc_stepp_i3","type_base_size":18,"type_scale_ratio":120,"enable_audio":true,"enable_animations":true,"enable_animated_images":true,"product_card_color_scheme":"color__bg-shade-1 color__text","product_card_color_border":"","product_card_overlay_text":"!color__dark","product_card_color_overlay":"","product_card_ratio":"aspect-[1\/1] aspect-w-1 aspect-h-1","product_card_crop":"cover","product_card_image_style":"standard","product_card_border_style":"image","product_card_alignment":"center","product_card_title_font":"type__heading type--big","product_card_enable_review_badge":false,"product_card_enable_review_text":true,"product_card_show_text_on_hover":false,"blog_card_color_border":"","blog_card_ratio":"aspect-[1\/1] aspect-w-1 aspect-h-1","blog_card_border_style":"image","blog_card_enable_author":false,"blog_card_enable_tags":true,"enable_quick_desktop":true,"enable_quick_image":true,"plan_selection":"dropdowns","pagination_type":"scroll","enable_region":true,"enable_language":true,"layout_horizontal":"window","layout_header_position":"dynamic","layout_gap_size":10,"animated_header":"fade","product_variant_selection":"buttons","price_enable_zeros":false,"price_enable_currency":false,"icon_style":"round","navigation_button_content":"icon","navigation_button_color":"btn btn--minimal","sections":{"theme__cart":{"type":"theme__cart","blocks":{"empty_cart_Y7Tb7A":{"type":"empty_cart","settings":{"heading":"","content":"<h3>Your cart is empty! <\/h3><h3>You should buy The Duo<\/h3><h3><\/h3>","button_label":"Shop the Duo","url":"shopify:\/\/products\/bundle","enable_autoplay":true,"enable_mute_toggle":true,"enable_loop":true,"spacing_minimum_height":250,"enable_padding":true,"color_scheme":"color__bg-overlay-1 color__text","color_border":"","color_text":"color__text","color_button":"btn--small btn--secondary !color__secondary","enable_gradient":false,"layout_y_alignment":"justify-end","layout_x_alignment":"left"}},"upsell_checkbox_HAXEQK":{"type":"upsell_checkbox","settings":{"variant_id":"48075561140507","label":"Add shipping protection - $5"}},"upsell_featured_EMY6ht":{"type":"upsell_featured","settings":{"products":"all-products-1"}}},"block_order":["empty_cart_Y7Tb7A","upsell_checkbox_HAXEQK","upsell_featured_EMY6ht"],"settings":{"top_color_scheme":"color__bg-body color__text","top_color_border":"color__border-divider-1","main_color_scheme_first":"color__bg-body color__text","main_color_scheme_second":"color__bg-body color__text","main_color_border":"color__border-divider-1","main_enable_cart_note":true,"main_enable_cart_share":true,"main_enable_cart_sku":false,"bottom_color_scheme":"color__bg-body color__text","bottom_color_border":"!color__border-transparent","bottom_color_button":"btn","cart_button_behavior":"checkout","bottom_disclaimer":"","show_continue_shopping_button":false,"show_button_prices":true,"show_cart_subtotals":true}},"theme__menu":{"type":"theme__menu","blocks":{"image_aaGYFH":{"type":"image","settings":{"menu":"women"}},"image_fAmBKm":{"type":"image","settings":{"menu":""}},"image_Nkhrxe":{"type":"image","settings":{"menu":""}},"image_pUGnJV":{"type":"image","settings":{"menu":""}}},"block_order":["image_aaGYFH","image_fAmBKm","image_Nkhrxe","image_pUGnJV"],"settings":{"top_color_scheme":"color__bg-body color__text","top_color_border":"color__border-divider-1","main_color_scheme":"color__bg-body color__text","main_color_border":"color__border-divider-1","show_search":false,"bottom_color_scheme":"color__bg-body color__text","bottom_color_border":"color__border-divider-1"}},"theme__search":{"type":"theme__search","settings":{"search_links":"","top_color_scheme":"color__bg-body color__text","top_color_border":"color__border-divider-1","main_color_scheme":"color__bg-body color__text","main_color_border":"color__border-divider-1"}}},"content_for_index":[]}},"platform_customizations":{"custom_css":["#template--24107868061986__banner_alternative_bi864K .gap-4.flex.flex-col.max-w-prose {width: 80%;}","@media (min-width: 1280px) {.window--narrow {max-width: 100%; }}","#template--24107868061986__banner_alternative_bi864K .w-full.h-full.flex.flex-row.flex-wrap.py-4.window--narrow.justify-start.items-center {justify-content: center;}","@media (max-width: 768px) {#template--24107868061986__liquid_p6iTVG .cozterra-image {order: -1; } #template--24107868061986__liquid_anagGy .zenith-image {order: -1; } #template--24107868061986__banner_alternative_bi864K .space-y-4 {text-align: center; } #template--24097052131618__banner_FQCQ3k .window--full {margin: auto; padding-left: 20px; padding-right: 20px; } .relative.flex-grow.no-underline.hover\\:no-underline.group\\\/banner {min-height: 250px !important; } h2 {text-align: center; } p {text-align: center; } .tech-content, .sustainability-content, .community-content {align-items: center; } .tech-image-container, .community-image-container {order: -1; } .tech-section, .sustainability-section {background-color: #ffffff; padding: 20px 20px !important; } .community-section {background-color: #ffffff; padding: 20px 20px 40px 20px !important; } .pillars-section {padding: 40px 20px 20px 20px; } .pillars-container {padding: 0 !important; }}","@media (min-width: 1280px) {.window--narrow {max-width: 1170px; } .window--narrow {width: 100%; }}","@media (min-width: 768px) {#template--24115367772450__text_Vry4XU .md\\:w-\\[50\\%\\] {width: 75% !important; } #template--24115367772450__text_Vry4XU p, #template--24115367772450__banner_dt7r6h p {margin-top: 30px; }}"]}}